pyredq/__init__.py
pyredq/queue.py
pyredq/version.py
pyredq-0.3.0.dist-info/LICENSE
pyredq-0.3.0.dist-info/METADATA
pyredq-0.3.0.dist-info/WHEEL
pyredq-0.3.0.dist-info/top_level.txt
pyredq-0.3.0.dist-info/RECORD
