Metadata-Version: 2.1
Name: pyredq
Version: 0.3.0
Summary: Light and fast ordered message queue for Python3 using Redis
Home-page: https://github.com/adrianchifor/pyredq
Author: Adrian Chifor
Author-email: me@adrianchifor.com
License: Apache License 2.0
Keywords: redis ordered distributed queue pubsub
Platform: UNKNOWN
Classifier: Development Status :: 4 - Beta
Classifier: Intended Audience :: Developers
Classifier: Topic :: Software Development :: Libraries :: Python Modules
Classifier: Topic :: System :: Distributed Computing
Classifier: License :: OSI Approved :: Apache Software License
Classifier: Programming Language :: Python :: 3.6
Classifier: Programming Language :: Python :: 3.7
Requires-Python: >=3.6
Requires-Dist: redis (>=3.4.1)
Requires-Dist: msgpack (>=1.0.0)
